{"result": {"stationName":"면목","stationID":721,"type":7,"laneName":"수도권 7호선","laneCity":"수도권","x":127.0875162,"y":37.5887571,"prevOBJ": {"station": [{"stationName":"상봉","stationID":720,"type":7,"laneName":"수도권 7호선","laneCity":"수도권","x":127.0857338,"y":37.5956273}]},"nextOBJ": {"station": [{"stationName":"사가정","stationID":722,"type":7,"laneName":"수도권 7호선","laneCity":"수도권","x":127.0885168,"y":37.5809707}]},"defaultInfo": {"address":"서울특별시 중랑구 면목동 282-6","new_address":"서울특별시 중랑구 면목로 407","tel":"02-6311-7211"},"useInfo": {"platform":2,"meetingPlace":1,"restroom":2,"offDoor":1,"crossOver":2,"publicPlace":0,"handicapCount":1,"parkingCount":0,"bicycleCount":1,"civilCount":0},"exitInfo": {"gate": [{"GateNo":"1","GateLink": ["동원시장","면목초등학교","면목본동"],"BUSSTOP": [{"StopName":"지하철7호선면목역","StopID":"108643","Bus": [{"BusNo":"272","Type":"11","BlID":"990","BusCityName":"서울"},{"BusNo":"262","Type":"11","BlID":"1439","BusCityName":"서울"},{"BusNo":"240","Type":"11","BlID":"1495","BusCityName":"서울"},{"BusNo":"2015","Type":"12","BlID":"947","BusCityName":"서울"},{"BusNo":"2230","Type":"12","BlID":"1714","BusCityName":"서울"}]},{"StopName":"면목역","StopID":"108685","Bus": [{"BusNo":"242","Type":"11","BlID":"585","BusCityName":"서울"},{"BusNo":"1213","Type":"12","BlID":"849","BusCityName":"서울"},{"BusNo":"2013","Type":"12","BlID":"944","BusCityName":"서울"},{"BusNo":"2227","Type":"12","BlID":"972","BusCityName":"서울"}]}]},{"GateNo":"2","GateLink": ["면목3.8동","서일대학 방면","멱목1치안센터","면목지구대"],"BUSSTOP": [{"StopName":"면목복개천","StopID":"108601","Bus": [{"BusNo":"242","Type":"11","BlID":"585","BusCityName":"서울"},{"BusNo":"1213","Type":"12","BlID":"849","BusCityName":"서울"},{"BusNo":"2013","Type":"12","BlID":"944","BusCityName":"서울"},{"BusNo":"2227","Type":"12","BlID":"972","BusCityName":"서울"}]},{"StopName":"면목본동주민센터","StopID":"108660","Bus": [{"BusNo":"272","Type":"11","BlID":"990","BusCityName":"서울"},{"BusNo":"262","Type":"11","BlID":"1439","BusCityName":"서울"},{"BusNo":"240","Type":"11","BlID":"1495","BusCityName":"서울"},{"BusNo":"2015","Type":"12","BlID":"947","BusCityName":"서울"},{"BusNo":"2230","Type":"12","BlID":"1714","BusCityName":"서울"}]},{"StopName":"지하철7호선면목역","StopID":"108670","Bus": [{"BusNo":"242","Type":"11","BlID":"585","BusCityName":"서울"},{"BusNo":"1213","Type":"12","BlID":"849","BusCityName":"서울"},{"BusNo":"2013","Type":"12","BlID":"944","BusCityName":"서울"},{"BusNo":"2227","Type":"12","BlID":"972","BusCityName":"서울"}]}]},{"GateNo":"3","GateLink": ["면목본동주민센터","면목초등학교","면목2동","면목역공원","중랑노인종합복지관","중랑구립면목정보도서관"],"BUSSTOP": [{"StopName":"면목복개천","StopID":"108597","Bus": [{"BusNo":"242","Type":"11","BlID":"585","BusCityName":"서울"},{"BusNo":"1213","Type":"12","BlID":"849","BusCityName":"서울"},{"BusNo":"2013","Type":"12","BlID":"944","BusCityName":"서울"},{"BusNo":"2227","Type":"12","BlID":"972","BusCityName":"서울"}]},{"StopName":"지하철7호선면목역","StopID":"108639","Bus": [{"BusNo":"272","Type":"11","BlID":"990","BusCityName":"서울"},{"BusNo":"262","Type":"11","BlID":"1439","BusCityName":"서울"},{"BusNo":"240","Type":"11","BlID":"1495","BusCityName":"서울"},{"BusNo":"2015","Type":"12","BlID":"947","BusCityName":"서울"},{"BusNo":"2230","Type":"12","BlID":"1714","BusCityName":"서울"}]}]}]}}}