{"result": {"Name": "신길온천","Address": "경기도 안산시 단원구 신길동 216-2","Tel": "1544-7788","LaneName": "수도권 4호선","UpWay": "당고개","DownWay": "오이도","Ord": {"TimeTable": [{"Hour": "5","UPList": {"Value": ["19(당고개)","24(당고개)","36(당고개)","48(당고개)","57(당고개)"]},"UP_Exp_Index": "","DOWNList": {"Value": ["33(오이도)","52(오이도)"]},"DOWN_Exp_Index": ""},{"Hour": "6","UPList": {"Value": ["02(당고개)","06(당고개)","15(당고개)","21(당고개)","27(당고개)","34(당고개)","41(당고개)","48(당고개)","58(당고개)"]},"UP_Exp_Index": "","DOWNList": {"Value": ["10(오이도)","27(오이도)","38(오이도)","45(오이도)"]},"DOWN_Exp_Index": ""},{"Hour": "7","UPList": {"Value": ["05(당고개)","13(당고개)","20(당고개)","31(당고개)","36(당고개)","50(당고개)"]},"UP_Exp_Index": "","DOWNList": {"Value": ["01(오이도)","16(오이도)","26(오이도)","41(오이도)","46(오이도)","51(오이도)"]},"DOWN_Exp_Index": ""},{"Hour": "8","UPList": {"Value": ["02(당고개)","15(당고개)","24(당고개)","35(당고개)","49(당고개)","58(당고개)"]},"UP_Exp_Index": "","DOWNList": {"Value": ["04(오이도)","10(오이도)","16(오이도)","22(오이도)","28(오이도)","34(오이도)","44(오이도)"]},"DOWN_Exp_Index": ""},{"Hour": "9","UPList": {"Value": ["13(당고개)","26(당고개)","35(당고개)","44(당고개)","52(안산)"]},"UP_Exp_Index": "","DOWNList": {"Value": ["00(오이도)","06(오이도)","18(오이도)","23(오이도)","36(오이도)","42(오이도)","55(오이도)"]},"DOWN_Exp_Index": ""},{"Hour": "10","UPList": {"Value": ["04(당고개)","09(안산)","24(당고개)","35(당고개)","46(당고개)","54(안산)"]},"UP_Exp_Index": "","DOWNList": {"Value": ["07(오이도)","21(오이도)","28(오이도)","40(오이도)","56(오이도)"]},"DOWN_Exp_Index": ""},{"Hour": "11","UPList": {"Value": ["06(당고개)","14(당고개)","37(당고개)","49(당고개)"]},"UP_Exp_Index": "","DOWNList": {"Value": ["02(오이도)","13(오이도)","32(오이도)","42(오이도)","53(오이도)"]},"DOWN_Exp_Index": ""},{"Hour": "12","UPList": {"Value": ["03(당고개)","16(당고개)","23(당고개)","36(당고개)","47(당고개)","58(당고개)"]},"UP_Exp_Index": "","DOWNList": {"Value": ["03(오이도)","17(오이도)","28(오이도)","40(오이도)","54(오이도)"]},"DOWN_Exp_Index": ""},{"Hour": "13","UPList": {"Value": ["13(당고개)","26(당고개)","37(당고개)","47(당고개)","54(당고개)"]},"UP_Exp_Index": "","DOWNList": {"Value": ["07(오이도)","17(오이도)","28(오이도)","35(오이도)","45(오이도)","58(오이도)"]},"DOWN_Exp_Index": ""},{"Hour": "14","UPList": {"Value": ["04(당고개)","17(당고개)","37(당고개)","48(당고개)"]},"UP_Exp_Index": "","DOWNList": {"Value": ["18(오이도)","29(오이도)","48(오이도)","55(오이도)"]},"DOWN_Exp_Index": ""},{"Hour": "15","UPList": {"Value": ["07(당고개)","14(당고개)","28(당고개)","41(당고개)","53(당고개)"]},"UP_Exp_Index": "","DOWNList": {"Value": ["09(오이도)","20(오이도)","33(오이도)","45(오이도)","58(오이도)"]},"DOWN_Exp_Index": ""},{"Hour": "16","UPList": {"Value": ["05(당고개)","16(당고개)","26(당고개)","41(당고개)","56(당고개)"]},"UP_Exp_Index": "","DOWNList": {"Value": ["05(오이도)","18(오이도)","30(오이도)","42(오이도)","56(오이도)"]},"DOWN_Exp_Index": ""},{"Hour": "17","UPList": {"Value": ["10(당고개)","17(당고개)","31(당고개)","45(당고개)","53(당고개)","59(당고개)"]},"UP_Exp_Index": "","DOWNList": {"Value": ["09(오이도)","20(오이도)","30(오이도)","37(오이도)","47(오이도)","58(오이도)"]},"DOWN_Exp_Index": ""},{"Hour": "18","UPList": {"Value": ["10(당고개)","18(당고개)","26(당고개)","34(당고개)","48(당고개)","55(당고개)"]},"UP_Exp_Index": "","DOWNList": {"Value": ["09(오이도)","19(오이도)","29(오이도)","44(오이도)","58(오이도)"]},"DOWN_Exp_Index": ""},{"Hour": "19","UPList": {"Value": ["00(당고개)","19(당고개)","32(당고개)","39(당고개)","48(당고개)"]},"UP_Exp_Index": "","DOWNList": {"Value": ["12(오이도)","26(오이도)","34(오이도)","46(오이도)","58(오이도)"]},"DOWN_Exp_Index": ""},{"Hour": "20","UPList": {"Value": ["05(당고개)","18(당고개)","32(당고개)","48(당고개)","57(당고개)"]},"UP_Exp_Index": "","DOWNList": {"Value": ["10(오이도)","18(오이도)","29(오이도)","43(오이도)","57(오이도)"]},"DOWN_Exp_Index": ""},{"Hour": "21","UPList": {"Value": ["13(당고개)","22(당고개)","32(당고개)","43(당고개)","55(당고개)"]},"UP_Exp_Index": "","DOWNList": {"Value": ["04(오이도)","19(오이도)","32(오이도)","41(오이도)","51(오이도)","57(오이도)"]},"DOWN_Exp_Index": ""},{"Hour": "22","UPList": {"Value": ["07(당고개)","21(당고개)","38(당고개)","56(당고개)"]},"UP_Exp_Index": "","DOWNList": {"Value": ["07(오이도)","18(오이도)","29(오이도)","39(오이도)","48(오이도)","57(오이도)"]},"DOWN_Exp_Index": ""},{"Hour": "23","UPList": {"Value": ["14(당고개)","34(한성대입구)","48(금정)"]},"UP_Exp_Index": "","DOWNList": {"Value": ["11(오이도)","22(오이도)","34(오이도)","45(오이도)","57(오이도)"]},"DOWN_Exp_Index": ""},{"Hour": "24","UPList": {"Value": ["05(사당)","29(금정)"]},"UP_Exp_Index": "","DOWNList": {"Value": ["11(오이도)","27(오이도)","38(오이도)","54(오이도)"]},"DOWN_Exp_Index": ""}]},"Sat": {"TimeTable": [{"Hour": "5","UPList": {"Value": ["35(당고개)","47(당고개)","57(당고개)"]},"UP_Exp_Index": "","DOWNList": {"Value": []},"DOWN_Exp_Index": ""},{"Hour": "6","UPList": {"Value": ["07(당고개)","17(당고개)","27(당고개)","37(당고개)","47(당고개)","57(당고개)"]},"UP_Exp_Index": "","DOWNList": {"Value": ["10(오이도)","27(오이도)","45(오이도)"]},"DOWN_Exp_Index": ""},{"Hour": "7","UPList": {"Value": ["07(당고개)","22(당고개)","27(당고개)","36(당고개)","46(당고개)","57(당고개)"]},"UP_Exp_Index": "","DOWNList": {"Value": ["01(오이도)","16(오이도)","27(오이도)","37(오이도)","57(오이도)"]},"DOWN_Exp_Index": ""},{"Hour": "8","UPList": {"Value": ["17(당고개)","37(당고개)","50(당고개)","57(당고개)"]},"UP_Exp_Index": "","DOWNList": {"Value": ["17(오이도)","37(오이도)","57(오이도)"]},"DOWN_Exp_Index": ""},{"Hour": "9","UPList": {"Value": ["17(당고개)","37(당고개)","57(당고개)"]},"UP_Exp_Index": "","DOWNList": {"Value": ["07(오이도)","17(오이도)","37(오이도)","54(오이도)"]},"DOWN_Exp_Index": ""},{"Hour": "10","UPList": {"Value": ["18(당고개)","37(당고개)","52(당고개)","57(당고개)"]},"UP_Exp_Index": "","DOWNList": {"Value": ["07(오이도)","17(오이도)","32(오이도)","37(오이도)","57(오이도)"]},"DOWN_Exp_Index": ""},{"Hour": "11","UPList": {"Value": ["17(당고개)","37(당고개)","57(당고개)"]},"UP_Exp_Index": "","DOWNList": {"Value": ["17(오이도)","29(오이도)","37(오이도)"]},"DOWN_Exp_Index": ""},{"Hour": "12","UPList": {"Value": ["05(안산)","19(당고개)","37(당고개)","56(당고개)"]},"UP_Exp_Index": "","DOWNList": {"Value": ["00(오이도)","17(오이도)","32(오이도)","37(오이도)","57(오이도)"]},"DOWN_Exp_Index": ""},{"Hour": "13","UPList": {"Value": ["06(당고개)","17(당고개)","37(당고개)","47(당고개)","57(당고개)"]},"UP_Exp_Index": "","DOWNList": {"Value": ["07(오이도)","17(오이도)","37(오이도)","47(오이도)","59(오이도)"]},"DOWN_Exp_Index": ""},{"Hour": "14","UPList": {"Value": ["07(당고개)","17(당고개)","22(당고개)","37(당고개)","52(당고개)","57(당고개)"]},"UP_Exp_Index": "","DOWNList": {"Value": ["07(오이도)","17(오이도)","32(오이도)","37(오이도)","57(오이도)"]},"DOWN_Exp_Index": ""},{"Hour": "15","UPList": {"Value": ["17(당고개)","27(당고개)","37(당고개)","44(당고개)","56(당고개)"]},"UP_Exp_Index": "","DOWNList": {"Value": ["09(오이도)","17(오이도)","27(오이도)","37(오이도)","59(오이도)"]},"DOWN_Exp_Index": ""},{"Hour": "16","UPList": {"Value": ["17(당고개)","37(당고개)","47(당고개)"]},"UP_Exp_Index": "","DOWNList": {"Value": ["17(오이도)","36(오이도)","57(오이도)"]},"DOWN_Exp_Index": ""},{"Hour": "17","UPList": {"Value": ["07(당고개)","17(당고개)","27(당고개)","37(당고개)","47(당고개)","57(당고개)"]},"UP_Exp_Index": "","DOWNList": {"Value": ["07(오이도)","19(오이도)","28(오이도)","37(오이도)","47(오이도)","57(오이도)"]},"DOWN_Exp_Index": ""},{"Hour": "18","UPList": {"Value": ["06(당고개)","17(당고개)","37(당고개)","47(당고개)"]},"UP_Exp_Index": "","DOWNList": {"Value": ["07(오이도)","17(오이도)","37(오이도)","57(오이도)"]},"DOWN_Exp_Index": ""},{"Hour": "19","UPList": {"Value": ["07(당고개)","17(당고개)","37(당고개)","57(당고개)"]},"UP_Exp_Index": "","DOWNList": {"Value": ["17(오이도)","37(오이도)","57(오이도)"]},"DOWN_Exp_Index": ""},{"Hour": "20","UPList": {"Value": ["19(당고개)","41(당고개)","58(당고개)"]},"UP_Exp_Index": "","DOWNList": {"Value": ["17(오이도)","37(오이도)","47(오이도)","57(오이도)"]},"DOWN_Exp_Index": ""},{"Hour": "21","UPList": {"Value": ["10(당고개)","30(당고개)","46(당고개)"]},"UP_Exp_Index": "","DOWNList": {"Value": ["17(오이도)","27(오이도)","37(오이도)","57(오이도)"]},"DOWN_Exp_Index": ""},{"Hour": "22","UPList": {"Value": ["02(당고개)","18(당고개)","35(한성대입구)","47(금정)"]},"UP_Exp_Index": "","DOWNList": {"Value": ["09(오이도)","21(오이도)","27(오이도)","37(오이도)","49(오이도)","56(오이도)"]},"DOWN_Exp_Index": ""},{"Hour": "23","UPList": {"Value": ["05(사당)","18(금정)","28(금정)"]},"UP_Exp_Index": "","DOWNList": {"Value": ["09(오이도)","21(오이도)","35(오이도)","52(오이도)"]},"DOWN_Exp_Index": ""},{"Hour": "24","UPList": {"Value": []},"UP_Exp_Index": "","DOWNList": {"Value": ["01(오이도)","12(오이도)"]},"DOWN_Exp_Index": ""}]},"Sun": {"TimeTable": [{"Hour": "5","UPList": {"Value": ["35(당고개)","47(당고개)","57(당고개)"]},"UP_Exp_Index": "","DOWNList": {"Value": []},"DOWN_Exp_Index": ""},{"Hour": "6","UPList": {"Value": ["07(당고개)","17(당고개)","27(당고개)","37(당고개)","47(당고개)","57(당고개)"]},"UP_Exp_Index": "","DOWNList": {"Value": ["10(오이도)","27(오이도)","45(오이도)"]},"DOWN_Exp_Index": ""},{"Hour": "7","UPList": {"Value": ["07(당고개)","22(당고개)","27(당고개)","36(당고개)","46(당고개)","57(당고개)"]},"UP_Exp_Index": "","DOWNList": {"Value": ["01(오이도)","16(오이도)","27(오이도)","37(오이도)","57(오이도)"]},"DOWN_Exp_Index": ""},{"Hour": "8","UPList": {"Value": ["17(당고개)","37(당고개)","50(당고개)","57(당고개)"]},"UP_Exp_Index": "","DOWNList": {"Value": ["17(오이도)","37(오이도)","57(오이도)"]},"DOWN_Exp_Index": ""},{"Hour": "9","UPList": {"Value": ["17(당고개)","37(당고개)","57(당고개)"]},"UP_Exp_Index": "","DOWNList": {"Value": ["07(오이도)","17(오이도)","37(오이도)","54(오이도)"]},"DOWN_Exp_Index": ""},{"Hour": "10","UPList": {"Value": ["18(당고개)","37(당고개)","52(당고개)","57(당고개)"]},"UP_Exp_Index": "","DOWNList": {"Value": ["07(오이도)","17(오이도)","32(오이도)","37(오이도)","57(오이도)"]},"DOWN_Exp_Index": ""},{"Hour": "11","UPList": {"Value": ["17(당고개)","37(당고개)","57(당고개)"]},"UP_Exp_Index": "","DOWNList": {"Value": ["17(오이도)","29(오이도)","37(오이도)"]},"DOWN_Exp_Index": ""},{"Hour": "12","UPList": {"Value": ["05(안산)","19(당고개)","37(당고개)","56(당고개)"]},"UP_Exp_Index": "","DOWNList": {"Value": ["00(오이도)","17(오이도)","32(오이도)","37(오이도)","57(오이도)"]},"DOWN_Exp_Index": ""},{"Hour": "13","UPList": {"Value": ["06(당고개)","17(당고개)","37(당고개)","47(당고개)","57(당고개)"]},"UP_Exp_Index": "","DOWNList": {"Value": ["07(오이도)","17(오이도)","37(오이도)","47(오이도)","59(오이도)"]},"DOWN_Exp_Index": ""},{"Hour": "14","UPList": {"Value": ["07(당고개)","17(당고개)","22(당고개)","37(당고개)","52(당고개)","57(당고개)"]},"UP_Exp_Index": "","DOWNList": {"Value": ["07(오이도)","17(오이도)","32(오이도)","37(오이도)","57(오이도)"]},"DOWN_Exp_Index": ""},{"Hour": "15","UPList": {"Value": ["17(당고개)","27(당고개)","37(당고개)","44(당고개)","56(당고개)"]},"UP_Exp_Index": "","DOWNList": {"Value": ["09(오이도)","17(오이도)","27(오이도)","37(오이도)","59(오이도)"]},"DOWN_Exp_Index": ""},{"Hour": "16","UPList": {"Value": ["17(당고개)","37(당고개)","47(당고개)"]},"UP_Exp_Index": "","DOWNList": {"Value": ["17(오이도)","36(오이도)","57(오이도)"]},"DOWN_Exp_Index": ""},{"Hour": "17","UPList": {"Value": ["07(당고개)","17(당고개)","27(당고개)","37(당고개)","47(당고개)","57(당고개)"]},"UP_Exp_Index": "","DOWNList": {"Value": ["07(오이도)","19(오이도)","28(오이도)","37(오이도)","47(오이도)","57(오이도)"]},"DOWN_Exp_Index": ""},{"Hour": "18","UPList": {"Value": ["06(당고개)","17(당고개)","37(당고개)","47(당고개)"]},"UP_Exp_Index": "","DOWNList": {"Value": ["07(오이도)","17(오이도)","37(오이도)","57(오이도)"]},"DOWN_Exp_Index": ""},{"Hour": "19","UPList": {"Value": ["07(당고개)","17(당고개)","37(당고개)","57(당고개)"]},"UP_Exp_Index": "","DOWNList": {"Value": ["17(오이도)","37(오이도)","57(오이도)"]},"DOWN_Exp_Index": ""},{"Hour": "20","UPList": {"Value": ["19(당고개)","41(당고개)","58(당고개)"]},"UP_Exp_Index": "","DOWNList": {"Value": ["17(오이도)","37(오이도)","47(오이도)","57(오이도)"]},"DOWN_Exp_Index": ""},{"Hour": "21","UPList": {"Value": ["10(당고개)","30(당고개)","46(당고개)"]},"UP_Exp_Index": "","DOWNList": {"Value": ["17(오이도)","27(오이도)","37(오이도)","57(오이도)"]},"DOWN_Exp_Index": ""},{"Hour": "22","UPList": {"Value": ["02(당고개)","18(당고개)","35(한성대입구)","47(금정)"]},"UP_Exp_Index": "","DOWNList": {"Value": ["09(오이도)","21(오이도)","27(오이도)","37(오이도)","49(오이도)","56(오이도)"]},"DOWN_Exp_Index": ""},{"Hour": "23","UPList": {"Value": ["05(사당)","18(금정)","28(금정)"]},"UP_Exp_Index": "","DOWNList": {"Value": ["09(오이도)","21(오이도)","35(오이도)","52(오이도)"]},"DOWN_Exp_Index": ""},{"Hour": "24","UPList": {"Value": []},"UP_Exp_Index": "","DOWNList": {"Value": ["01(오이도)","12(오이도)"]},"DOWN_Exp_Index": ""}]}}}