{"result": {"Name": "오이도","Address": "경기도 시흥시 정왕동 878","Tel": "1544-7788","LaneName": "수인선","DownWay": "인천","Ord": {"TimeTable": [{"Hour": "5","UPList": {"Value": []},"UP_Exp_Index": "","DOWNList": {"Value": ["30(인천)","45(인천)","58(인천)"]},"DOWN_Exp_Index": ""},{"Hour": "6","UPList": {"Value": []},"UP_Exp_Index": "","DOWNList": {"Value": ["10(인천)","23(인천)","35(인천)","47(인천)","57(인천)"]},"DOWN_Exp_Index": ""},{"Hour": "7","UPList": {"Value": []},"UP_Exp_Index": "","DOWNList": {"Value": ["06(인천)","15(인천)","24(인천)","34(인천)","43(인천)","52(인천)"]},"DOWN_Exp_Index": ""},{"Hour": "8","UPList": {"Value": []},"UP_Exp_Index": "","DOWNList": {"Value": ["00(인천)","07(인천)","16(인천)","25(인천)","34(인천)","44(인천)"]},"DOWN_Exp_Index": ""},{"Hour": "9","UPList": {"Value": []},"UP_Exp_Index": "","DOWNList": {"Value": ["00(인천)","13(인천)","28(인천)","43(인천)"]},"DOWN_Exp_Index": ""},{"Hour": "10","UPList": {"Value": []},"UP_Exp_Index": "","DOWNList": {"Value": ["00(인천)","15(인천)","30(인천)","45(인천)"]},"DOWN_Exp_Index": ""},{"Hour": "11","UPList": {"Value": []},"UP_Exp_Index": "","DOWNList": {"Value": ["00(인천)","15(인천)","30(인천)","45(인천)"]},"DOWN_Exp_Index": ""},{"Hour": "12","UPList": {"Value": []},"UP_Exp_Index": "","DOWNList": {"Value": ["00(인천)","15(인천)","30(인천)","45(인천)"]},"DOWN_Exp_Index": ""},{"Hour": "13","UPList": {"Value": []},"UP_Exp_Index": "","DOWNList": {"Value": ["00(인천)","15(인천)","30(인천)","45(인천)"]},"DOWN_Exp_Index": ""},{"Hour": "14","UPList": {"Value": []},"UP_Exp_Index": "","DOWNList": {"Value": ["00(인천)","15(인천)","30(인천)","45(인천)"]},"DOWN_Exp_Index": ""},{"Hour": "15","UPList": {"Value": []},"UP_Exp_Index": "","DOWNList": {"Value": ["00(인천)","15(인천)","30(인천)","45(인천)"]},"DOWN_Exp_Index": ""},{"Hour": "16","UPList": {"Value": []},"UP_Exp_Index": "","DOWNList": {"Value": ["00(인천)","15(인천)","30(인천)","45(인천)"]},"DOWN_Exp_Index": ""},{"Hour": "17","UPList": {"Value": []},"UP_Exp_Index": "","DOWNList": {"Value": ["00(인천)","15(인천)","30(인천)","45(인천)"]},"DOWN_Exp_Index": ""},{"Hour": "18","UPList": {"Value": []},"UP_Exp_Index": "","DOWNList": {"Value": ["00(인천)","10(인천)","20(인천)","32(인천)","44(인천)","56(인천)"]},"DOWN_Exp_Index": ""},{"Hour": "19","UPList": {"Value": []},"UP_Exp_Index": "","DOWNList": {"Value": ["08(인천)","20(인천)","32(인천)","44(인천)","56(인천)"]},"DOWN_Exp_Index": ""},{"Hour": "20","UPList": {"Value": []},"UP_Exp_Index": "","DOWNList": {"Value": ["08(인천)","25(인천)","40(인천)","55(인천)"]},"DOWN_Exp_Index": ""},{"Hour": "21","UPList": {"Value": []},"UP_Exp_Index": "","DOWNList": {"Value": ["10(인천)","24(인천)","39(인천)","55(인천)"]},"DOWN_Exp_Index": ""},{"Hour": "22","UPList": {"Value": []},"UP_Exp_Index": "","DOWNList": {"Value": ["10(인천)","25(인천)","40(인천)","55(인천)"]},"DOWN_Exp_Index": ""},{"Hour": "23","UPList": {"Value": []},"UP_Exp_Index": "","DOWNList": {"Value": ["13(인천)","30(인천)","53(인천)"]},"DOWN_Exp_Index": ""},{"Hour": "24","UPList": {"Value": []},"UP_Exp_Index": "","DOWNList": {"Value": []},"DOWN_Exp_Index": ""}]},"Sat": {"TimeTable": [{"Hour": "5","UPList": {"Value": []},"UP_Exp_Index": "","DOWNList": {"Value": ["30(인천)","50(인천)"]},"DOWN_Exp_Index": ""},{"Hour": "6","UPList": {"Value": []},"UP_Exp_Index": "","DOWNList": {"Value": ["10(인천)","25(인천)","40(인천)","55(인천)"]},"DOWN_Exp_Index": ""},{"Hour": "7","UPList": {"Value": []},"UP_Exp_Index": "","DOWNList": {"Value": ["10(인천)","25(인천)","40(인천)","55(인천)"]},"DOWN_Exp_Index": ""},{"Hour": "8","UPList": {"Value": []},"UP_Exp_Index": "","DOWNList": {"Value": ["10(인천)","25(인천)","40(인천)","55(인천)"]},"DOWN_Exp_Index": ""},{"Hour": "9","UPList": {"Value": []},"UP_Exp_Index": "","DOWNList": {"Value": ["10(인천)","25(인천)","40(인천)","55(인천)"]},"DOWN_Exp_Index": ""},{"Hour": "10","UPList": {"Value": []},"UP_Exp_Index": "","DOWNList": {"Value": ["09(인천)","23(인천)","36(인천)","51(인천)"]},"DOWN_Exp_Index": ""},{"Hour": "11","UPList": {"Value": []},"UP_Exp_Index": "","DOWNList": {"Value": ["05(인천)","20(인천)","35(인천)","50(인천)"]},"DOWN_Exp_Index": ""},{"Hour": "12","UPList": {"Value": []},"UP_Exp_Index": "","DOWNList": {"Value": ["05(인천)","20(인천)","35(인천)","50(인천)"]},"DOWN_Exp_Index": ""},{"Hour": "13","UPList": {"Value": []},"UP_Exp_Index": "","DOWNList": {"Value": ["05(인천)","20(인천)","35(인천)","50(인천)"]},"DOWN_Exp_Index": ""},{"Hour": "14","UPList": {"Value": []},"UP_Exp_Index": "","DOWNList": {"Value": ["04(인천)","20(인천)","35(인천)","50(인천)"]},"DOWN_Exp_Index": ""},{"Hour": "15","UPList": {"Value": []},"UP_Exp_Index": "","DOWNList": {"Value": ["05(인천)","20(인천)","35(인천)","50(인천)"]},"DOWN_Exp_Index": ""},{"Hour": "16","UPList": {"Value": []},"UP_Exp_Index": "","DOWNList": {"Value": ["05(인천)","20(인천)","35(인천)","50(인천)"]},"DOWN_Exp_Index": ""},{"Hour": "17","UPList": {"Value": []},"UP_Exp_Index": "","DOWNList": {"Value": ["05(인천)","20(인천)","35(인천)","50(인천)"]},"DOWN_Exp_Index": ""},{"Hour": "18","UPList": {"Value": []},"UP_Exp_Index": "","DOWNList": {"Value": ["05(인천)","23(인천)","40(인천)","55(인천)"]},"DOWN_Exp_Index": ""},{"Hour": "19","UPList": {"Value": []},"UP_Exp_Index": "","DOWNList": {"Value": ["10(인천)","25(인천)","40(인천)","55(인천)"]},"DOWN_Exp_Index": ""},{"Hour": "20","UPList": {"Value": []},"UP_Exp_Index": "","DOWNList": {"Value": ["10(인천)","25(인천)","40(인천)","55(인천)"]},"DOWN_Exp_Index": ""},{"Hour": "21","UPList": {"Value": []},"UP_Exp_Index": "","DOWNList": {"Value": ["10(인천)","25(인천)","40(인천)","55(인천)"]},"DOWN_Exp_Index": ""},{"Hour": "22","UPList": {"Value": []},"UP_Exp_Index": "","DOWNList": {"Value": ["10(인천)","25(인천)","40(인천)","55(인천)"]},"DOWN_Exp_Index": ""},{"Hour": "23","UPList": {"Value": []},"UP_Exp_Index": "","DOWNList": {"Value": ["10(인천)","30(인천)","50(인천)"]},"DOWN_Exp_Index": ""},{"Hour": "24","UPList": {"Value": []},"UP_Exp_Index": "","DOWNList": {"Value": []},"DOWN_Exp_Index": ""}]},"Sun": {"TimeTable": [{"Hour": "5","UPList": {"Value": []},"UP_Exp_Index": "","DOWNList": {"Value": ["30(인천)","50(인천)"]},"DOWN_Exp_Index": ""},{"Hour": "6","UPList": {"Value": []},"UP_Exp_Index": "","DOWNList": {"Value": ["10(인천)","30(인천)","50(인천)"]},"DOWN_Exp_Index": ""},{"Hour": "7","UPList": {"Value": []},"UP_Exp_Index": "","DOWNList": {"Value": ["10(인천)","30(인천)","50(인천)"]},"DOWN_Exp_Index": ""},{"Hour": "8","UPList": {"Value": []},"UP_Exp_Index": "","DOWNList": {"Value": ["10(인천)","30(인천)","50(인천)"]},"DOWN_Exp_Index": ""},{"Hour": "9","UPList": {"Value": []},"UP_Exp_Index": "","DOWNList": {"Value": ["10(인천)","30(인천)","45(인천)","58(인천)"]},"DOWN_Exp_Index": ""},{"Hour": "10","UPList": {"Value": []},"UP_Exp_Index": "","DOWNList": {"Value": ["15(인천)","30(인천)","44(인천)"]},"DOWN_Exp_Index": ""},{"Hour": "11","UPList": {"Value": []},"UP_Exp_Index": "","DOWNList": {"Value": ["00(인천)","16(인천)","31(인천)","45(인천)"]},"DOWN_Exp_Index": ""},{"Hour": "12","UPList": {"Value": []},"UP_Exp_Index": "","DOWNList": {"Value": ["00(인천)","15(인천)","30(인천)","45(인천)"]},"DOWN_Exp_Index": ""},{"Hour": "13","UPList": {"Value": []},"UP_Exp_Index": "","DOWNList": {"Value": ["00(인천)","15(인천)","30(인천)","45(인천)"]},"DOWN_Exp_Index": ""},{"Hour": "14","UPList": {"Value": []},"UP_Exp_Index": "","DOWNList": {"Value": ["00(인천)","15(인천)","30(인천)","45(인천)"]},"DOWN_Exp_Index": ""},{"Hour": "15","UPList": {"Value": []},"UP_Exp_Index": "","DOWNList": {"Value": ["00(인천)","15(인천)","30(인천)","45(인천)"]},"DOWN_Exp_Index": ""},{"Hour": "16","UPList": {"Value": []},"UP_Exp_Index": "","DOWNList": {"Value": ["00(인천)","15(인천)","30(인천)","45(인천)"]},"DOWN_Exp_Index": ""},{"Hour": "17","UPList": {"Value": []},"UP_Exp_Index": "","DOWNList": {"Value": ["00(인천)","15(인천)","30(인천)","45(인천)"]},"DOWN_Exp_Index": ""},{"Hour": "18","UPList": {"Value": []},"UP_Exp_Index": "","DOWNList": {"Value": ["00(인천)","15(인천)","30(인천)","45(인천)"]},"DOWN_Exp_Index": ""},{"Hour": "19","UPList": {"Value": []},"UP_Exp_Index": "","DOWNList": {"Value": ["00(인천)","15(인천)","30(인천)","45(인천)"]},"DOWN_Exp_Index": ""},{"Hour": "20","UPList": {"Value": []},"UP_Exp_Index": "","DOWNList": {"Value": ["00(인천)","15(인천)","30(인천)","45(인천)"]},"DOWN_Exp_Index": ""},{"Hour": "21","UPList": {"Value": []},"UP_Exp_Index": "","DOWNList": {"Value": ["00(인천)","20(인천)","40(인천)"]},"DOWN_Exp_Index": ""},{"Hour": "22","UPList": {"Value": []},"UP_Exp_Index": "","DOWNList": {"Value": ["00(인천)","15(인천)","30(인천)","45(인천)"]},"DOWN_Exp_Index": ""},{"Hour": "23","UPList": {"Value": []},"UP_Exp_Index": "","DOWNList": {"Value": ["00(인천)","15(인천)","30(인천)","50(인천)"]},"DOWN_Exp_Index": ""},{"Hour": "24","UPList": {"Value": []},"UP_Exp_Index": "","DOWNList": {"Value": []},"DOWN_Exp_Index": ""}]}}}